{
  "_fv": 33,
  "_type": "tool",
  "definition": {
    "renderType": 0,
    "texture": "diamondesword",
    "customModelName": "Normal",
    "name": "Diamond E Sword",
    "specialInfo": [],
    "creativeTab": {
      "value": "TOOLS"
    },
    "toolType": "Sword",
    "harvestLevel": 3,
    "efficiency": 12.0,
    "attackSpeed": 1.0,
    "enchantability": 15,
    "damageVsEntity": 18.0,
    "usageCount": 0,
    "blocksAffected": [],
    "hasGlow": false,
    "repairItems": [],
    "immuneToFire": false,
    "stayInGridWhenCrafting": false,
    "damageOnCrafting": false
  }
}